gpu_cluster_monitor/__init__.py
gpu_cluster_monitor/main.py
gpu_cluster_monitor-0.0.2.dist-info/LICENSE
gpu_cluster_monitor-0.0.2.dist-info/METADATA
gpu_cluster_monitor-0.0.2.dist-info/WHEEL
gpu_cluster_monitor-0.0.2.dist-info/entry_points.txt
gpu_cluster_monitor-0.0.2.dist-info/top_level.txt
gpu_cluster_monitor-0.0.2.dist-info/RECORD
