Metadata-Version: 2.1
Name: gpu-cluster-monitor
Version: 0.0.2
Summary: A CLI dashboard to monitor GPU utilization and other metrics on remote hosts via SSH.
Home-page: https://github.com/AgrawalAmey/gpu-cluster-monitor
Author: Amey Agrawal
Author-email: agrawalamey12@gmail.com
Keywords: GPU,Monitor,Dashboard,CLI,SSH,NVIDIA,NVIDIA-SMI,Rich
Classifier: Programming Language :: Python :: 3.10
Classifier: Programming Language :: Python :: 3.11
Classifier: License :: OSI Approved :: MIT License
Classifier: Topic :: System :: Monitoring
Requires-Python: >=3.10
License-File: LICENSE
Requires-Dist: rich>=13.0.0
Requires-Dist: pyyaml>=6.0
